README.md
setup.cfg
setup.py
mathlibs/__init__.py
mathlibs.egg-info/PKG-INFO
mathlibs.egg-info/SOURCES.txt
mathlibs.egg-info/dependency_links.txt
mathlibs.egg-info/not-zip-safe
mathlibs.egg-info/top_level.txt