Metadata-Version: 2.1
Name: mathlibs
Version: 0.3
Summary: math theorem
Home-page: https://github.com/SergeyBT/mathlibs
Author: Sergey Kudinov
Author-email: info@blagon-team.ml
License: MIT
Platform: UNKNOWN
